{
  "id": "did:web:dayneis.github.io",
  "@context": [
    "https://www.w3.org/ns/did/v1",
    {
      "@base": "did:web:dayneis.github.io"
    }
  ],
  "service": [
    {
      "id": "#linkeddomains",
      "type": "LinkedDomains",
      "serviceEndpoint": {
        "origins": [
          "https://dayneis.github.io/"
        ]
      }
    },
    {
      "id": "#hub",
      "type": "IdentityHub",
      "serviceEndpoint": {
        "instances": [
          "https://hub.did.msidentity.com/v1.0/c2ce0286-46e2-4c1b-88f6-615d4706d676"
        ]
      }
    }
  ],
  "verificationMethod": [
    {
      "id": "#73803ed1b0304ba4aa7f2cd764dbce91vcSigningKey-f7d56",
      "controller": "did:web:dayneis.github.io",
      "type": "JsonWebKey2020",
      "publicKeyJwk": {
        "crv": "P-256",
        "kty": "EC",
        "x": "_BozeIfSJy7UwCj6Oj0Uft6QGc4_dQ6MLGdAqXktAS4",
        "y": "ePx_DOn20vP-lResbeXFoE0wF8sJQSRHUSg7Rn_a9So"
      }
    }
  ],
  "authentication": [
    "#73803ed1b0304ba4aa7f2cd764dbce91vcSigningKey-f7d56"
  ],
  "assertionMethod": [
    "#73803ed1b0304ba4aa7f2cd764dbce91vcSigningKey-f7d56"
  ]
}
